gitfluff/__init__.py
gitfluff/__main__.py
gitfluff/cli.py
gitfluff/downloader.py
gitfluff-0.8.0.dist-info/METADATA
gitfluff-0.8.0.dist-info/WHEEL
gitfluff-0.8.0.dist-info/entry_points.txt
gitfluff-0.8.0.dist-info/top_level.txt
gitfluff-0.8.0.dist-info/RECORD
