Metadata-Version: 2.1
Name: gitfluff
Version: 0.8.0
Summary: Commit message linter and formatter
Author-email: Na'aman Hirschfeld <nhirschfeld@gmail.com>
License: MIT
Project-URL: Homepage, https://github.com/Goldziher/gitfluff
Project-URL: Repository, https://github.com/Goldziher/gitfluff.git
Project-URL: Issues, https://github.com/Goldziher/gitfluff/issues
Keywords: git,commit,lint,conventional,format
Classifier: Development Status :: 3 - Alpha
Classifier: Intended Audience :: Developers
Classifier: License :: OSI Approved :: MIT License
Classifier: Programming Language :: Python :: 3
Classifier: Programming Language :: Python :: 3.8
Classifier: Programming Language :: Python :: 3.9
Classifier: Programming Language :: Python :: 3.10
Classifier: Programming Language :: Python :: 3.11
Classifier: Programming Language :: Python :: 3.12
Classifier: Topic :: Software Development :: Build Tools
Classifier: Environment :: Console
Requires-Python: >=3.8
Requires-Dist: certifi>=2024.7.4
